{"cameraMode":{"drawMode":0,"name":"Shaded","section":"Shading Mode"},"sceneLighting":false,"audioPlay":false,"sceneViewState":{"m_AlwaysRefresh":false,"showFog":true,"showSkybox":false,"showFlares":true,"showImageEffects":true,"showParticleSystems":true,"showVisualEffectGraphs":true,"m_FxEnabled":true},"in2DMode":false,"pivot":{"x":14.107649803161621,"y":6.7480597496032719,"z":735.4892578125},"rotation":{"x":-0.057826459407806399,"y":-0.9417405128479004,"z":0.21247507631778718,"w":-0.254446804523468},"size":0.6139349341392517,"orthographic":false}